apscale_nanopore/__init__.py
apscale_nanopore/__main__.py
apscale_nanopore/apscale_nanopore_gui.py
apscale_nanopore/default_settings.xlsx
apscale_nanopore/default_settings_nd.xlsx
apscale_nanopore-1.0.10.dist-info/LICENSE
apscale_nanopore-1.0.10.dist-info/METADATA
apscale_nanopore-1.0.10.dist-info/WHEEL
apscale_nanopore-1.0.10.dist-info/entry_points.txt
apscale_nanopore-1.0.10.dist-info/top_level.txt
apscale_nanopore-1.0.10.dist-info/RECORD
