Metadata-Version: 2.1
Name: apscale_nanopore
Version: 1.0.10
Summary: Advanced Pipeline for Simple yet Comprehensive AnaLysEs of DNA metabarcoding data - Nanopore application
Home-page: https://pypi.org/project/apscale_nanopore/
Author: Till-Hendrik Macher
Author-email: macher@uni-trier.de
License: MIT
Classifier: Programming Language :: Python :: 3
Classifier: License :: OSI Approved :: MIT License
Classifier: Operating System :: OS Independent
Requires-Python: >=3.10
License-File: LICENSE
Requires-Dist: Bio>=1.7.1
Requires-Dist: biopython>=1.85
Requires-Dist: cutadapt>=5.0
Requires-Dist: joblib>=1.4.2
Requires-Dist: ete3>=3.1.3
Requires-Dist: numpy>=1.26.4
Requires-Dist: pandas>=2.2.3
Requires-Dist: pyarrow>=19.0.0
Requires-Dist: xmltodict>=0.14.2
Requires-Dist: plotly>=6.1.1
Requires-Dist: tqdm>=4.67.1
